pykylin/__init__.py
pykylin-0.1.dist-info/WHEEL
pykylin-0.1.dist-info/METADATA
pykylin-0.1.dist-info/RECORD
