Metadata-Version: 2.1
Name: pykylin
Version: 0.1
Summary: pykylin
Keywords: 
